setup.py
snowplow_analytics_sdk/__init__.py
snowplow_analytics_sdk/event_transformer.py
snowplow_analytics_sdk/json_shredder.py
snowplow_analytics_sdk/run_manifests.py
snowplow_analytics_sdk/snowplow_event_transformation_exception.py
snowplow_analytics_sdk.egg-info/PKG-INFO
snowplow_analytics_sdk.egg-info/SOURCES.txt
snowplow_analytics_sdk.egg-info/dependency_links.txt
snowplow_analytics_sdk.egg-info/requires.txt
snowplow_analytics_sdk.egg-info/top_level.txt