Metadata-Version: 1.0
Name: snowplow-analytics-sdk
Version: 0.2.2
Summary: Snowplow Analytics Python SDK
Home-page: https://github.com/snowplow/snowplow-python-analytics-sdk
Author: Fred Blundun
Author-email: support@snowplowanalytics.com
License: UNKNOWN
Platform: UNKNOWN
